env_proxy/__init__.py
env_proxy/_sentinel.py
env_proxy/env_config.py
env_proxy/env_proxy.py
env_proxy/py.typed
env_proxy-1.1.1.dist-info/LICENSE.md
env_proxy-1.1.1.dist-info/METADATA
env_proxy-1.1.1.dist-info/WHEEL
env_proxy-1.1.1.dist-info/RECORD
