Metadata-Version: 2.3
Name: env-proxy
Version: 1.1.1
Summary: Creates a class used to query environmental variables with typehinting a conversion to basic Python types.
License: MIT
Author: Tomas Votava
Author-email: info@tomasvotava.eu
Requires-Python: >=3.10,<3.14
Classifier: License :: OSI Approved :: MIT License
Classifier: Programming Language :: Python :: 3
Classifier: Programming Language :: Python :: 3.10
Classifier: Programming Language :: Python :: 3.11
Classifier: Programming Language :: Python :: 3.12
Classifier: Programming Language :: Python :: 3.13
Project-URL: Homepage, https://github.com/tomasvotava/env-proxy
Project-URL: Repository, https://github.com/tomasvotava/env-proxy
